CHANGES.txt
README.md
setup.py
djinn_events/__init__.py
djinn_events/admin.py
djinn_events/search_indexes.py
djinn_events/settings.py
djinn_events/urls.py
djinn_events.egg-info/PKG-INFO
djinn_events.egg-info/SOURCES.txt
djinn_events.egg-info/dependency_links.txt
djinn_events.egg-info/entry_points.txt
djinn_events.egg-info/not-zip-safe
djinn_events.egg-info/requires.txt
djinn_events.egg-info/top_level.txt
djinn_events/forms/__init__.py
djinn_events/forms/event.py
djinn_events/management/__init__.py
djinn_events/models/__init__.py
djinn_events/models/event.py
djinn_events/views/__init__.py
djinn_events/views/eventviewlet.py